c_apidocs-1.0.0.dist-info/licenses/AUTHORS
capidocs/__init__.py
capidocs/kerneldoc.py
c_apidocs-1.0.0.dist-info/METADATA
c_apidocs-1.0.0.dist-info/WHEEL
c_apidocs-1.0.0.dist-info/top_level.txt
c_apidocs-1.0.0.dist-info/RECORD
