Metadata-Version: 2.4
Name: c-apidocs
Version: 1.0.0
Summary: API Documentation Utilities
Home-page: https://c-util.github.io/c-apidocs
Requires-Python: >=3.8
License-File: AUTHORS
Requires-Dist: hawkmoth>=0.20
Dynamic: license-file
